coolstring/CoolString.py
coolstring/__init__.py
coolstring-0.1.2.dist-info/METADATA
coolstring-0.1.2.dist-info/WHEEL
coolstring-0.1.2.dist-info/licenses/LICENSE
coolstring-0.1.2.dist-info/RECORD
