Metadata-Version: 2.4
Name: coolstring
Version: 0.1.2
Summary: A fun implementation of a string that can perform several operators and more
Project-URL: Documentation, https://coolstring.readthedocs.io/en/latest/
Project-URL: Repository, https://github.com/playlix42/coolstring
Author-email: DouglasAdams_42 <douglasadams_42@gmx.de>
License-File: LICENSE
Classifier: License :: OSI Approved :: GNU General Public License v3 (GPLv3)
Classifier: Operating System :: OS Independent
Classifier: Programming Language :: Python :: 3
Requires-Python: >=3.10
